_kSpider_internal.cpython-38-x86_64-linux-gnu.so
kSpider2_retina.libs/libbz2-a273e504.so.1.0.6
kSpider2_retina.libs/libgomp-a34b3233.so.1.0.0
kSpider2_retina.libs/libz-745e0a09.so.1.2.7
kSpider2/click_context.py
kSpider2/ks_indexing.py
kSpider2/kSpider_main.py
kSpider2/ks_pairwise.py
kSpider2/__init__.py
internal/kSpider_internal.py
internal/__init__.py
kSpider2_retina-2.0.3.dist-info/RECORD
kSpider2_retina-2.0.3.dist-info/top_level.txt
kSpider2_retina-2.0.3.dist-info/entry_points.txt
kSpider2_retina-2.0.3.dist-info/METADATA
kSpider2_retina-2.0.3.dist-info/WHEEL
